lzhlog/__init__.py
lzhlog/ftimer.py
lzhlog-25.0.0.dist-info/METADATA
lzhlog-25.0.0.dist-info/WHEEL
lzhlog-25.0.0.dist-info/top_level.txt
lzhlog-25.0.0.dist-info/RECORD
